APMonitor/__init__.py
APMonitor/apm.py
APMonitor/apm_class.py
APMonitor-0.34.dist-info/DESCRIPTION.rst
APMonitor-0.34.dist-info/METADATA
APMonitor-0.34.dist-info/RECORD
APMonitor-0.34.dist-info/WHEEL
APMonitor-0.34.dist-info/metadata.json
APMonitor-0.34.dist-info/top_level.txt
apm/__init__.py
apm/apm.py
